twidge/__init__.py
twidge/__main__.py
twidge/core.py
twidge/terminal.py
twidge/widgets/__init__.py
twidge/widgets/editors.py
twidge/widgets/filters.py
twidge/widgets/form.py
twidge/widgets/inline.py
twidge/widgets/simple.py
twidge/widgets/templater.py
twidge/widgets/wrappers.py
twidge-1.2.2.dist-info/LICENSE
twidge-1.2.2.dist-info/METADATA
twidge-1.2.2.dist-info/WHEEL
twidge-1.2.2.dist-info/entry_points.txt
twidge-1.2.2.dist-info/RECORD
