Metadata-Version: 2.1
Name: twidge
Version: 1.2.2
Summary: Terminal Widgets.
Home-page: https://github.com/aidaco/twidge
License: MIT
Author: Aidan Courtney
Author-email: aidanfc97@gmail.com
Requires-Python: >=3.11,<4.0
Classifier: License :: OSI Approved :: MIT License
Classifier: Programming Language :: Python :: 3
Classifier: Programming Language :: Python :: 3.11
Classifier: Programming Language :: Python :: 3.12
Classifier: Programming Language :: Python :: 3.13
Requires-Dist: rich
Requires-Dist: typer
Project-URL: Repository, https://github.com/aidaco/twidge
